[
  {
    "2011":"38.70",
    "2012":"42.50",
    "2013":"51.60",
    "2014":"55.10",
    "2015":"40.80",
    "REGION":"BAKEL"
  },
  {
    "2011":"9.50",
    "2012":"12.50",
    "2013":"13.80",
    "2014":"15.10",
    "2015":"16.30",
    "REGION":"BAMBEY"
  },
  {
    "2011":"17.40",
    "2012":"18.90",
    "2013":"23.10",
    "2014":"26.00",
    "2015":"35.60",
    "REGION":"BIGNONA"
  },
  {
    "2011":"6.20",
    "2012":"8.00",
    "2013":"8.20",
    "2014":"9.30",
    "2015":"15.50",
    "REGION":"BIRKELANE"
  },
  {
    "2011":"23.20",
    "2012":"23.20",
    "2013":"30.00",
    "2014":"34.80",
    "2015":"39.10",
    "REGION":"BOUNKILING"
  },
  {
    "2011":"10.50",
    "2012":"18.20",
    "2013":"21.00",
    "2014":"28.60",
    "2015":"28.50",
    "REGION":"DAGANA"
  },
  {
    "2011":"16.10",
    "2012":"16.30",
    "2013":"19.50",
    "2014":"18.40",
    "2015":"26.70",
    "REGION":"DAKAR"
  },
  {
    "2011":"13.50",
    "2012":"14.60",
    "2013":"16.70",
    "2014":"19.10",
    "2015":"22.60",
    "REGION":"DIOURBEL"
  },
  {
    "2011":"6.50",
    "2012":"8.90",
    "2013":"12.10",
    "2014":"15.30",
    "2015":"18.40",
    "REGION":"FATICK"
  },
  {
    "2011":"15.30",
    "2012":"23.90",
    "2013":"32.00",
    "2014":"38.20",
    "2015":"45.70",
    "REGION":"FOUNDIOUGNE"
  },
  {
    "2011":"17.30",
    "2012":"21.10",
    "2013":"28.20",
    "2014":"30.40",
    "2015":"35.00",
    "REGION":"GOSSAS"
  },
  {
    "2011":"13.10",
    "2012":"14.90",
    "2013":"17.60",
    "2014":"21.40",
    "2015":"24.80",
    "REGION":"GOUDIRY"
  },
  {
    "2011":"25.60",
    "2012":"28.10",
    "2013":"30.80",
    "2014":"37.30",
    "2015":"39.70",
    "REGION":"GOUDOMP"
  },
  {
    "2011":"56.50",
    "2012":"54.60",
    "2013":"63.50",
    "2014":"63.70",
    "2015":"74.70",
    "REGION":"GUEDIAWAYE"
  },
  {
    "2011":"22.40",
    "2012":"24.40",
    "2013":"28.90",
    "2014":"31.90",
    "2015":"34.20",
    "REGION":"GUINGUINEO"
  },
  {
    "2011":"38.70",
    "2012":"42.50",
    "2013":"51.60",
    "2014":"55.10",
    "2015":"40.80",
    "REGION":"KAFFRINE"
  },
  {
    "2011":"9.50",
    "2012":"12.50",
    "2013":"13.80",
    "2014":"15.10",
    "2015":"16.30",
    "REGION":"KANEL"
  },
  {
    "2011":"17.40",
    "2012":"18.90",
    "2013":"23.10",
    "2014":"26.00",
    "2015":"35.60",
    "REGION":"KAOLACK"
  },
  {
    "2011":"6.20",
    "2012":"8.00",
    "2013":"8.20",
    "2014":"9.30",
    "2015":"15.50",
    "REGION":"KEBEMER"
  },
  {
    "2011":"23.20",
    "2012":"23.20",
    "2013":"30.00",
    "2014":"34.80",
    "2015":"39.10",
    "REGION":"KÉDOUGOU"
  },
  {
    "2011":"10.50",
    "2012":"18.20",
    "2013":"21.00",
    "2014":"28.60",
    "2015":"28.50",
    "REGION":"KOLDA"
  },
  {
    "2011":"16.10",
    "2012":"16.30",
    "2013":"19.50",
    "2014":"18.40",
    "2015":"26.70",
    "REGION":"KOUMPENTOUM"
  },
  {
    "2011":"13.50",
    "2012":"14.60",
    "2013":"16.70",
    "2014":"19.10",
    "2015":"22.60",
    "REGION":"KOUNGHEUL"
  },
  {
    "2011":"6.50",
    "2012":"8.90",
    "2013":"12.10",
    "2014":"15.30",
    "2015":"18.40",
    "REGION":"LINGUERE"
  },
  {
    "2011":"15.30",
    "2012":"23.90",
    "2013":"32.00",
    "2014":"38.20",
    "2015":"45.70",
    "REGION":"LOUGA"
  },
  {
    "2011":"17.30",
    "2012":"21.10",
    "2013":"28.20",
    "2014":"30.40",
    "2015":"35.00",
    "REGION":"MALEM HODAR"
  },
  {
    "2011":"13.10",
    "2012":"14.90",
    "2013":"17.60",
    "2014":"21.40",
    "2015":"24.80",
    "REGION":"MATAM"
  },
  {
    "2011":"25.60",
    "2012":"28.10",
    "2013":"30.80",
    "2014":"37.30",
    "2015":"39.70",
    "REGION":"MBACKE"
  },
  {
    "2011":"56.50",
    "2012":"54.60",
    "2013":"63.50",
    "2014":"63.70",
    "2015":"74.70",
    "REGION":"MBOUR"
  },
  {
    "2011":"22.40",
    "2012":"24.40",
    "2013":"28.90",
    "2014":"31.90",
    "2015":"34.20",
    "REGION":"MEDINA YORO FOULAH"
  },
  {
    "2011":"38.70",
    "2012":"42.50",
    "2013":"51.60",
    "2014":"55.10",
    "2015":"40.80",
    "REGION":"NIORO DU RIP"
  },
  {
    "2011":"9.50",
    "2012":"12.50",
    "2013":"13.80",
    "2014":"15.10",
    "2015":"16.30",
    "REGION":"OUSSOUYE"
  },
  {
    "2011":"17.40",
    "2012":"18.90",
    "2013":"23.10",
    "2014":"26.00",
    "2015":"35.60",
    "REGION":"PIKINE"
  },
  {
    "2011":"6.20",
    "2012":"8.00",
    "2013":"8.20",
    "2014":"9.30",
    "2015":"15.50",
    "REGION":"PODOR"
  },
  {
    "2011":"23.20",
    "2012":"23.20",
    "2013":"30.00",
    "2014":"34.80",
    "2015":"39.10",
    "REGION":"RANEROU"
  },
  {
    "2011":"10.50",
    "2012":"18.20",
    "2013":"21.00",
    "2014":"28.60",
    "2015":"28.50",
    "REGION":"RUFISQUE"
  },
  {
    "2011":"16.10",
    "2012":"16.30",
    "2013":"19.50",
    "2014":"18.40",
    "2015":"26.70",
    "REGION":"SALÉMATA"
  },
  {
    "2011":"13.50",
    "2012":"14.60",
    "2013":"16.70",
    "2014":"19.10",
    "2015":"22.60",
    "REGION":"SAMINE"
  },
  {
    "2011":"6.50",
    "2012":"8.90",
    "2013":"12.10",
    "2014":"15.30",
    "2015":"18.40",
    "REGION":"SARAYA"
  },
  {
    "2011":"15.30",
    "2012":"23.90",
    "2013":"32.00",
    "2014":"38.20",
    "2015":"45.70",
    "REGION":"SÉDHIOU"
  },
  {
    "2011":"17.30",
    "2012":"21.10",
    "2013":"28.20",
    "2014":"30.40",
    "2015":"35.00",
    "REGION":"ST LOUIS"
  },
  {
    "2011":"13.10",
    "2012":"14.90",
    "2013":"17.60",
    "2014":"21.40",
    "2015":"24.80",
    "REGION":"TAMBACOUNDA"
  },
  {
    "2011":"25.60",
    "2012":"28.10",
    "2013":"30.80",
    "2014":"37.30",
    "2015":"39.70",
    "REGION":"THIES"
  },
  {
    "2011":"56.50",
    "2012":"54.60",
    "2013":"63.50",
    "2014":"63.70",
    "2015":"74.70",
    "REGION":"TIVAOUANNE"
  },
  {
    "2011":"22.40",
    "2012":"24.40",
    "2013":"28.90",
    "2014":"31.90",
    "2015":"34.20",
    "REGION":"VELINGARA"
  },
  {
    "2011":"38.70",
    "2012":"42.50",
    "2013":"51.60",
    "2014":"55.10",
    "2015":"40.80",
    "REGION":"ZIGUINCHOR"
  }
]